{
    "id": 1,
    "metafields": [
        { "name": "Website", "value": "https://thecaversham.co.uk" },
        { "name": "Phone", "value": "0118 947 8600" },
        { "name": "Email", "value": "info@thecaversham.co.uk" },
        { "name": "Address", "value": "The Caversham, Mapledurham, Reading, Berkshire, RG4 7UT" }
    ],
    "updatedAt": "2024-10-16T12:50:17.552Z",
    "version": "1.41",
    "name": "The Caversham",
    "courseName": "Eyston Course",
    "coords": { "lat": "51.48967273", "lng": "-1.00563921" },
    "boxes": [
        { "name": "Black", "hexBackground": "000000", "hexColour": "ffffff" },
        { "name": "Gold", "hexBackground": "DAA520", "hexColour": "000000" },
        { "name": "Blue", "hexBackground": "1434A4", "hexColour": "ffffff" },
        { "name": "Green", "hexBackground": "2b912b", "hexColour": "ffffff" },
        { "name": "Orange", "hexBackground": "df621a", "hexColour": "ffffff" }
    ],
    "pins": [],
    "quadrants": [],
    "markers": [
        {
            "name": "Black",
            "colours": ["Black"],
            "sr": 131,
            "cr": 76,
            "ladies": { "sr": null, "cr": null },
            "par": 72,
            "parL": null,
            "tees": [
                { "no": 1, "colour": "Black" },
                { "no": 2, "colour": "Black" },
                { "no": 3, "colour": "Black" },
                { "no": 4, "colour": "Black" },
                { "no": 5, "colour": "Black" },
                { "no": 6, "colour": "Black" },
                { "no": 7, "colour": "Black" },
                { "no": 8, "colour": "Black" },
                { "no": 9, "colour": "Black" },
                { "no": 10, "colour": "Black" },
                { "no": 11, "colour": "Black" },
                { "no": 12, "colour": "Black" },
                { "no": 13, "colour": "Black" },
                { "no": 14, "colour": "Black" },
                { "no": 15, "colour": "Black" },
                { "no": 16, "colour": "Black" },
                { "no": 17, "colour": "Black" },
                { "no": 18, "colour": "Black" }
            ]
        },
        {
            "name": "Gold",
            "colours": ["Gold"],
            "sr": 126,
            "cr": 73.599999999999994,
            "ladies": { "sr": null, "cr": null },
            "par": 72,
            "parL": null,
            "tees": [
                { "no": 1, "colour": "Gold" },
                { "no": 2, "colour": "Gold" },
                { "no": 3, "colour": "Gold" },
                { "no": 4, "colour": "Gold" },
                { "no": 5, "colour": "Gold" },
                { "no": 6, "colour": "Gold" },
                { "no": 7, "colour": "Gold" },
                { "no": 8, "colour": "Gold" },
                { "no": 9, "colour": "Gold" },
                { "no": 10, "colour": "Gold" },
                { "no": 11, "colour": "Gold" },
                { "no": 12, "colour": "Gold" },
                { "no": 13, "colour": "Gold" },
                { "no": 14, "colour": "Gold" },
                { "no": 15, "colour": "Gold" },
                { "no": 16, "colour": "Gold" },
                { "no": 17, "colour": "Gold" },
                { "no": 18, "colour": "Gold" }
            ]
        },
        {
            "name": "Gold / Blue",
            "colours": ["Gold", "Blue"],
            "sr": 129,
            "cr": 72.900000000000006,
            "ladies": { "sr": null, "cr": null },
            "par": 72,
            "parL": null,
            "tees": [
                { "no": 1, "colour": "Blue" },
                { "no": 2, "colour": "Gold" },
                { "no": 3, "colour": "Blue" },
                { "no": 4, "colour": "Blue" },
                { "no": 5, "colour": "Gold" },
                { "no": 6, "colour": "Blue" },
                { "no": 7, "colour": "Gold" },
                { "no": 8, "colour": "Blue" },
                { "no": 9, "colour": "Gold" },
                { "no": 10, "colour": "Blue" },
                { "no": 11, "colour": "Gold" },
                { "no": 12, "colour": "Blue" },
                { "no": 13, "colour": "Gold" },
                { "no": 14, "colour": "Blue" },
                { "no": 15, "colour": "Blue" },
                { "no": 16, "colour": "Blue" },
                { "no": 17, "colour": "Gold" },
                { "no": 18, "colour": "Gold" }
            ]
        },
        {
            "name": "Blue",
            "colours": ["Blue"],
            "sr": 126,
            "cr": 72.299999999999997,
            "ladies": { "sr": null, "cr": null },
            "par": 72,
            "parL": null,
            "tees": [
                { "no": 1, "colour": "Blue" },
                { "no": 2, "colour": "Blue" },
                { "no": 3, "colour": "Blue" },
                { "no": 4, "colour": "Blue" },
                { "no": 5, "colour": "Blue" },
                { "no": 6, "colour": "Blue" },
                { "no": 7, "colour": "Blue" },
                { "no": 8, "colour": "Blue" },
                { "no": 9, "colour": "Blue" },
                { "no": 10, "colour": "Blue" },
                { "no": 11, "colour": "Blue" },
                { "no": 12, "colour": "Blue" },
                { "no": 13, "colour": "Blue" },
                { "no": 14, "colour": "Blue" },
                { "no": 15, "colour": "Blue" },
                { "no": 16, "colour": "Blue" },
                { "no": 17, "colour": "Blue" },
                { "no": 18, "colour": "Blue" }
            ]
        },
        {
            "name": "Blue / Green",
            "colours": ["Blue", "Green"],
            "sr": 126,
            "cr": 71.299999999999997,
            "ladies": { "sr": null, "cr": null },
            "par": 72,
            "parL": null,
            "tees": [
                { "no": 1, "colour": "Green" },
                { "no": 2, "colour": "Blue" },
                { "no": 3, "colour": "Green" },
                { "no": 4, "colour": "Blue" },
                { "no": 5, "colour": "Blue" },
                { "no": 6, "colour": "Green" },
                { "no": 7, "colour": "Blue" },
                { "no": 8, "colour": "Green" },
                { "no": 9, "colour": "Blue" },
                { "no": 10, "colour": "Green" },
                { "no": 11, "colour": "Blue" },
                { "no": 12, "colour": "Green" },
                { "no": 13, "colour": "Blue" },
                { "no": 14, "colour": "Green" },
                { "no": 15, "colour": "Green" },
                { "no": 16, "colour": "Blue" },
                { "no": 17, "colour": "Blue" },
                { "no": 18, "colour": "Blue" }
            ]
        },
        {
            "name": "Green",
            "colours": ["Green"],
            "sr": 124,
            "cr": 69.900000000000006,
            "ladies": { "sr": 138, "cr": 76.400000000000006 },
            "par": 72,
            "parL": null,
            "tees": [
                { "no": 1, "colour": "Green" },
                { "no": 2, "colour": "Green" },
                { "no": 3, "colour": "Green" },
                { "no": 4, "colour": "Green" },
                { "no": 5, "colour": "Green" },
                { "no": 6, "colour": "Green" },
                { "no": 7, "colour": "Green" },
                { "no": 8, "colour": "Green" },
                { "no": 9, "colour": "Green" },
                { "no": 10, "colour": "Green" },
                { "no": 11, "colour": "Green" },
                { "no": 12, "colour": "Green" },
                { "no": 13, "colour": "Green" },
                { "no": 14, "colour": "Green" },
                { "no": 15, "colour": "Green" },
                { "no": 16, "colour": "Green" },
                { "no": 17, "colour": "Green" },
                { "no": 18, "colour": "Green" }
            ]
        },
        {
            "name": "Green / Orange",
            "colours": ["Green", "Orange"],
            "sr": 124,
            "cr": 68.299999999999997,
            "ladies": { "sr": 134, "cr": 74.799999999999997 },
            "par": 72,
            "parL": null,
            "tees": [
                { "no": 1, "colour": "Orange" },
                { "no": 2, "colour": "Green" },
                { "no": 3, "colour": "Orange" },
                { "no": 4, "colour": "Orange" },
                { "no": 5, "colour": "Green" },
                { "no": 6, "colour": "Orange" },
                { "no": 7, "colour": "Green" },
                { "no": 8, "colour": "Orange" },
                { "no": 9, "colour": "Green" },
                { "no": 10, "colour": "Orange" },
                { "no": 11, "colour": "Green" },
                { "no": 12, "colour": "Orange" },
                { "no": 13, "colour": "Green" },
                { "no": 14, "colour": "Orange" },
                { "no": 15, "colour": "Orange" },
                { "no": 16, "colour": "Orange" },
                { "no": 17, "colour": "Green" },
                { "no": 18, "colour": "Green" }
            ]
        },
        {
            "name": "Orange",
            "colours": ["Orange"],
            "sr": 121,
            "cr": 67.299999999999997,
            "ladies": { "sr": 127, "cr": 73.599999999999994 },
            "par": 72,
            "parL": null,
            "tees": [
                { "no": 1, "colour": "Orange" },
                { "no": 2, "colour": "Orange" },
                { "no": 3, "colour": "Orange" },
                { "no": 4, "colour": "Orange" },
                { "no": 5, "colour": "Orange" },
                { "no": 6, "colour": "Orange" },
                { "no": 7, "colour": "Orange" },
                { "no": 8, "colour": "Orange" },
                { "no": 9, "colour": "Orange" },
                { "no": 10, "colour": "Orange" },
                { "no": 11, "colour": "Orange" },
                { "no": 12, "colour": "Orange" },
                { "no": 13, "colour": "Orange" },
                { "no": 14, "colour": "Orange" },
                { "no": 15, "colour": "Orange" },
                { "no": 16, "colour": "Orange" },
                { "no": 17, "colour": "Orange" },
                { "no": 18, "colour": "Orange" }
            ]
        }
    ],
    "holes": [
        {
            "no": 1,
            "tees": [
                { "colour": "Black", "coords": { "lat": 51.489522859877027, "lng": -1.0065123438835146 }, "par": 4, "parL": null },
                { "colour": "Gold", "coords": { "lat": 51.48928896726725, "lng": -1.0067322850227358 }, "par": 4, "parL": null },
                { "colour": "Blue", "coords": { "lat": 51.489175361852418, "lng": -1.0068878531455996 }, "par": 4, "parL": null },
                { "colour": "Green", "coords": { "lat": 51.489065097502625, "lng": -1.0070756077766421 }, "par": 4, "parL": null },
                { "colour": "Orange", "coords": { "lat": 51.48894815017352, "lng": -1.0072901844978335 }, "par": 4, "parL": null }
            ],
            "par": 4,
            "parL": null,
            "si": 10,
            "siL": 10,
            "checkpoints": [
                {
                    "type": "bunker",
                    "name": "Right Green",
                    "key": "bunker-Right Green",
                    "back": { "lat": 51.487574829587771, "lng": -1.009575426578522 },
                    "coord": { "lat": 51.487499705129579, "lng": -1.0098221898078921 },
                    "front": { "lat": 51.487424580671394, "lng": -1.0100689530372622 }
                },
                {
                    "type": "bunker",
                    "name": "Left FW",
                    "key": "bunker-Left FW",
                    "back": { "lat": 51.487381945684149, "lng": -1.008875370025635 },
                    "coord": { "lat": 51.487315585478107, "lng": -1.0089048743247988 },
                    "front": { "lat": 51.487249225272066, "lng": -1.0089343786239626 }
                },
                {
                    "type": "bunker",
                    "name": "Right FW",
                    "key": "bunker-Right FW",
                    "back": { "lat": 51.487912203327838, "lng": -1.0088405013084414 },
                    "coord": { "lat": 51.487786996686424, "lng": -1.0089786350727084 },
                    "front": { "lat": 51.487661790045017, "lng": -1.0091167688369753 }
                }
            ],
            "green": { "front": { "lat": 51.487367667792185, "lng": -1.009737700223923 }, "back": { "lat": 51.487230773733124, "lng": -1.0100904107093813 } },
            "pins": [{ "key": "", "quadrant": "", "coord": { "lat": 51.487299220762651, "lng": -1.0099140554666521 } }]
        },
        {
            "no": 2,
            "tees": [
                { "colour": "Black", "coords": { "lat": 51.48694350125588, "lng": -1.0099884867668154 }, "par": 3, "parL": null },
                { "colour": "Gold", "coords": { "lat": 51.486829889996841, "lng": -1.0098382830619814 }, "par": 3, "parL": null },
                { "colour": "Blue", "coords": { "lat": 51.486679521718699, "lng": -1.0097095370292666 }, "par": 3, "parL": null },
                { "colour": "Green", "coords": { "lat": 51.486525811410772, "lng": -1.0095861554145815 }, "par": 3, "parL": null },
                { "colour": "Orange", "coords": { "lat": 51.486398832939443, "lng": -1.009473502635956 }, "par": 3, "parL": null }
            ],
            "par": 3,
            "parL": null,
            "si": 12,
            "siL": 12,
            "checkpoints": [
                {
                    "type": "bunker",
                    "name": "Left Green",
                    "key": "bunker-Left Green",
                    "back": { "lat": 51.48586536014524, "lng": -1.0080680251121523 },
                    "coord": { "lat": 51.485850334710094, "lng": -1.0079875588417055 },
                    "front": { "lat": 51.485835309274947, "lng": -1.0079070925712588 }
                },
                {
                    "type": "bunker",
                    "name": "Right Green",
                    "key": "bunker-Right Green",
                    "back": { "lat": 51.485567354805994, "lng": -1.0082745552062991 },
                    "coord": { "lat": 51.485533129965646, "lng": -1.0082343220710757 },
                    "front": { "lat": 51.48549890512529, "lng": -1.0081940889358523 }
                }
            ],
            "green": { "front": { "lat": 51.485740873664938, "lng": -1.0081927478313448 }, "back": { "lat": 51.485539173266467, "lng": -1.0079600661993029 } },
            "pins": [{ "key": "", "quadrant": "", "coord": { "lat": 51.485640023465706, "lng": -1.0080764070153239 } }]
        },
        {
            "no": 3,
            "tees": [
                { "colour": "Black", "coords": { "lat": 51.485203272638969, "lng": -1.0082718729972842 }, "par": 4, "parL": null },
                { "colour": "Gold", "coords": { "lat": 51.485079632124844, "lng": -1.0077461600303652 }, "par": 4, "parL": null },
                { "colour": "Blue", "coords": { "lat": 51.48502616585278, "lng": -1.0075798630714419 }, "par": 4, "parL": null },
                { "colour": "Green", "coords": { "lat": 51.484972699517982, "lng": -1.0074564814567568 }, "par": 4, "parL": null },
                { "colour": "Orange", "coords": { "lat": 51.484902524858441, "lng": -1.007300913333893 }, "par": 4, "parL": null }
            ],
            "par": 4,
            "parL": null,
            "si": 4,
            "siL": 4,
            "checkpoints": [
                {
                    "type": "bunker",
                    "name": "Left Green",
                    "key": "bunker-Left Green",
                    "back": { "lat": 51.483589667161695, "lng": -1.0038220882415774 },
                    "coord": { "lat": 51.483532901521912, "lng": -1.0037885606288912 },
                    "front": { "lat": 51.483476135882135, "lng": -1.0037550330162051 }
                },
                {
                    "type": "bunker",
                    "name": "Left Green",
                    "key": "bunker-Left Green",
                    "back": { "lat": 51.48345109809916, "lng": -1.0034921765327456 },
                    "coord": { "lat": 51.483376801639835, "lng": -1.0034640133380892 },
                    "front": { "lat": 51.483302505180511, "lng": -1.0034358501434328 }
                },
                {
                    "type": "bunker",
                    "name": "Right Green",
                    "key": "bunker-Right Green",
                    "back": { "lat": 51.483217275555141, "lng": -1.0038676857948305 },
                    "coord": { "lat": 51.483167187824236, "lng": -1.0038006305694582 },
                    "front": { "lat": 51.483117100093338, "lng": -1.0037335753440859 }
                },
                {
                    "type": "bunker",
                    "name": "Right FW",
                    "key": "bunker-Right FW",
                    "back": { "lat": 51.483486078623514, "lng": -1.0041949152946474 },
                    "coord": { "lat": 51.483432652021563, "lng": -1.0041721165180209 },
                    "front": { "lat": 51.483379225419604, "lng": -1.0041493177413943 }
                },
                {
                    "name": "Right FW",
                    "type": "bunker",
                    "coord": { "lat": 51.483998661763216, "lng": -1.0050237178802492 },
                    "key": "1",
                    "back": { "lat": 51.483921827873715, "lng": -1.0049003362655642 },
                    "front": { "lat": 51.484035408360278, "lng": -1.0051953792572024 }
                }
            ],
            "green": { "front": { "lat": 51.483385374610975, "lng": -1.0037925839424136 }, "back": { "lat": 51.48319489365349, "lng": -1.0035243630409243 } },
            "pins": [{ "key": "", "quadrant": "", "coord": { "lat": 51.483305700518713, "lng": -1.0036772489547732 } }]
        },
        {
            "no": 4,
            "tees": [
                { "colour": "Black", "coords": { "lat": 51.482380540268181, "lng": -1.0046938061714175 }, "par": 4, "parL": null },
                { "colour": "Gold", "coords": { "lat": 51.482156636583319, "lng": -1.0050210356712344 }, "par": 4, "parL": null },
                { "colour": "Blue", "coords": { "lat": 51.482017642296007, "lng": -1.0050880908966067 }, "par": 4, "parL": null },
                { "colour": "Green", "coords": { "lat": 51.481809082417314, "lng": -1.0051175951957705 }, "par": 4, "parL": null },
                { "colour": "Orange", "coords": { "lat": 51.481672065143208, "lng": -1.005230247974396 }, "par": 4, "parL": null }
            ],
            "par": 4,
            "parL": null,
            "si": 16,
            "siL": 16,
            "checkpoints": [
                {
                    "type": "bunker",
                    "name": "Left Green",
                    "key": "bunker-Left Green",
                    "back": { "lat": 51.480148523464422, "lng": -1.0076723992824557 },
                    "coord": { "lat": 51.480119512381613, "lng": -1.0077813640236857 },
                    "front": { "lat": 51.480090501298804, "lng": -1.0078903287649157 }
                },
                {
                    "type": "bunker",
                    "name": "Right Green",
                    "key": "bunker-Right Green",
                    "back": { "lat": 51.480356400833209, "lng": -1.0077334195375445 },
                    "coord": { "lat": 51.480365792859658, "lng": -1.0078591480851176 },
                    "front": { "lat": 51.480375184886114, "lng": -1.0079848766326907 }
                },
                {
                    "type": "bunker",
                    "name": "Left FW",
                    "key": "bunker-Left FW",
                    "back": { "lat": 51.480276809595104, "lng": -1.0074457526206972 },
                    "coord": { "lat": 51.480261364894012, "lng": -1.0074843093752863 },
                    "front": { "lat": 51.480245920192921, "lng": -1.0075228661298754 }
                },
                {
                    "type": "bunker",
                    "name": "Right FW",
                    "key": "bunker-Right FW",
                    "back": { "lat": 51.480852028129448, "lng": -1.0062655806541445 },
                    "coord": { "lat": 51.480735985366735, "lng": -1.0066679120063784 },
                    "front": { "lat": 51.480619942604029, "lng": -1.0070702433586123 }
                },
                {
                    "name": "Layup",
                    "type": "checkpoint",
                    "coord": { "lat": 51.480667964369133, "lng": -1.0059356689453127 },
                    "key": "0",
                    "front": { "lat": 51.480846758882528, "lng": -1.0059383511543276 },
                    "back": { "lat": 51.480479298050987, "lng": -1.0059490799903872 }
                }
            ],
            "green": { "front": { "lat": 51.480242907569952, "lng": -1.0077736526727679 }, "back": { "lat": 51.480217862091706, "lng": -1.0081974416971209 } },
            "pins": [{ "key": "", "quadrant": "", "coord": { "lat": 51.480230384830833, "lng": -1.0079855471849444 } }]
        },
        {
            "no": 5,
            "tees": [
                { "colour": "Black", "coords": { "lat": 51.480375980578252, "lng": -1.0085132718086245 }, "par": 5, "parL": null },
                { "colour": "Gold", "coords": { "lat": 51.479968256618683, "lng": -1.0082879662513735 }, "par": 5, "parL": null },
                { "colour": "Blue", "coords": { "lat": 51.479797813555244, "lng": -1.0080626606941225 }, "par": 5, "parL": null },
                { "colour": "Green", "coords": { "lat": 51.479694210597572, "lng": -1.0077944397926333 }, "par": 5, "parL": null },
                { "colour": "Orange", "coords": { "lat": 51.479473635774745, "lng": -1.0075315833091738 }, "par": 5, "parL": null }
            ],
            "par": 5,
            "parL": null,
            "si": 18,
            "siL": 18,
            "checkpoints": [
                {
                    "type": "bunker",
                    "name": "Right Green",
                    "key": "bunker-Right Green",
                    "back": { "lat": 51.476126868742128, "lng": -1.0083550214767458 },
                    "coord": { "lat": 51.476083870095614, "lng": -1.0083664208650591 },
                    "front": { "lat": 51.476040871449101, "lng": -1.0083778202533724 }
                },
                {
                    "name": "Right FW",
                    "type": "bunker",
                    "coord": { "lat": 51.476329832598452, "lng": -1.0083838552236559 },
                    "key": "5",
                    "back": { "lat": 51.476379092918137, "lng": -1.008400619029999 },
                    "front": { "lat": 51.47628057227876, "lng": -1.0083670914173128 }
                },
                {
                    "type": "bunker",
                    "name": "Left Green",
                    "key": "bunker-Left Green",
                    "back": { "lat": 51.476086121356253, "lng": -1.0079446434974673 },
                    "coord": { "lat": 51.476014317681724, "lng": -1.0079661011695864 },
                    "front": { "lat": 51.475942514007194, "lng": -1.0079875588417055 }
                },
                {
                    "name": "Left FW",
                    "type": "bunker",
                    "coord": { "lat": 51.476376131060164, "lng": -1.0078863054513933 },
                    "key": "4",
                    "back": { "lat": 51.476440002426813, "lng": -1.0078963637351992 },
                    "front": { "lat": 51.476312259693515, "lng": -1.0078762471675875 }
                },
                {
                    "name": "Left FW",
                    "type": "bunker",
                    "coord": { "lat": 51.47692606088868, "lng": -1.0075449943542483 },
                    "key": "3",
                    "back": { "lat": 51.476889308563031, "lng": -1.0076200962066653 },
                    "front": { "lat": 51.476979518764061, "lng": -1.00750207901001 }
                },
                {
                    "name": "Right FW",
                    "type": "bunker",
                    "coord": { "lat": 51.478114978178766, "lng": -1.0073599219322207 },
                    "key": "1",
                    "back": { "lat": 51.478187613434507, "lng": -1.0073840618133547 },
                    "front": { "lat": 51.478042342923025, "lng": -1.0073357820510866 }
                },
                {
                    "name": "Left FW",
                    "type": "bunker",
                    "coord": { "lat": 51.47801057341065, "lng": -1.0067322850227358 },
                    "key": "2",
                    "back": { "lat": 51.478074025043661, "lng": -1.0067752003669741 },
                    "front": { "lat": 51.477947121777639, "lng": -1.0066893696784975 }
                },
                {
                    "name": "Layup",
                    "type": "checkpoint",
                    "coord": { "lat": 51.478122867019941, "lng": -1.0070192813873293 },
                    "key": "0",
                    "front": { "lat": 51.477929173038163, "lng": -1.0069924592971804 },
                    "back": { "lat": 51.478316561001719, "lng": -1.0070461034774782 }
                }
            ],
            "green": { "front": { "lat": 51.476172727763867, "lng": -1.0082155466079714 }, "back": { "lat": 51.47590137680352, "lng": -1.0082396864891054 } },
            "pins": [{ "key": "", "quadrant": "", "coord": { "lat": 51.476037052283694, "lng": -1.0082276165485384 } }]
        },
        {
            "no": 6,
            "tees": [
                { "colour": "Black", "coords": { "lat": 51.475691239116479, "lng": -1.0068234801292422 }, "par": 4, "parL": null },
                { "colour": "Gold", "coords": { "lat": 51.475858378696699, "lng": -1.0068234801292422 }, "par": 4, "parL": null },
                { "colour": "Blue", "coords": { "lat": 51.475861721012357, "lng": -1.0065981745719912 }, "par": 4, "parL": null },
                { "colour": "Green", "coords": { "lat": 51.476018809570995, "lng": -1.0066571831703188 }, "par": 4, "parL": null },
                { "colour": "Orange", "coords": { "lat": 51.476226031948535, "lng": -1.006603538990021 }, "par": 4, "parL": null }
            ],
            "par": 4,
            "parL": null,
            "si": 2,
            "siL": 2,
            "checkpoints": [],
            "green": { "front": { "lat": 51.478374548539669, "lng": -1.0048332810401919 }, "back": { "lat": 51.478568391748276, "lng": -1.0045918822288515 } },
            "pins": [{ "key": "", "quadrant": "", "coord": { "lat": 51.47848406358419, "lng": -1.004680395126343 } }]
        },
        {
            "no": 7,
            "tees": [
                { "colour": "Black", "coords": { "lat": 51.47756568182708, "lng": -1.006002724170685 }, "par": 5, "parL": null },
                { "colour": "Gold", "coords": { "lat": 51.477878277740601, "lng": -1.0057318210601809 }, "par": 5, "parL": null },
                { "colour": "Blue", "coords": { "lat": 51.477976769425503, "lng": -1.0058471560478213 }, "par": 5, "parL": null },
                { "colour": "Green", "coords": { "lat": 51.478090402742197, "lng": -1.0057827830314638 }, "par": 5, "parL": null },
                { "colour": "Orange", "coords": { "lat": 51.478518196218772, "lng": -1.0054609179496767 }, "par": 5, "parL": null }
            ],
            "par": 5,
            "parL": null,
            "si": 6,
            "siL": 6,
            "checkpoints": [
                {
                    "name": "Water",
                    "type": "water",
                    "coord": { "lat": 51.481914079046263, "lng": -1.0040849447250368 },
                    "key": "5",
                    "back": { "lat": 51.482020983042077, "lng": -1.0040634870529177 },
                    "front": { "lat": 51.481783789462533, "lng": -1.0041439533233645 }
                },
                {
                    "type": "bunker",
                    "name": "Left Green",
                    "key": "bunker-Left Green",
                    "back": { "lat": 51.482216371122881, "lng": -1.0041157901287081 },
                    "coord": { "lat": 51.482256859513569, "lng": -1.0040775686502459 },
                    "front": { "lat": 51.482297347904264, "lng": -1.0040393471717837 }
                },
                {
                    "name": "Left FW",
                    "type": "bunker",
                    "coord": { "lat": 51.481526549960684, "lng": -1.00475549697876 },
                    "key": "6",
                    "back": { "lat": 51.48163011409045, "lng": -1.00475549697876 },
                    "front": { "lat": 51.481456393481089, "lng": -1.0047394037246706 }
                },
                {
                    "name": "Mid FW",
                    "type": "bunker",
                    "coord": { "lat": 51.480373965546562, "lng": -1.0048359632492068 },
                    "key": "4",
                    "back": { "lat": 51.480487554869669, "lng": -1.0048037767410281 },
                    "front": { "lat": 51.480267057689936, "lng": -1.0048681497573855 }
                },
                {
                    "name": "Left FW",
                    "type": "bunker",
                    "coord": { "lat": 51.48029712554996, "lng": -1.0051685571670534 },
                    "key": "3",
                    "back": { "lat": 51.480360602078193, "lng": -1.0051363706588747 },
                    "front": { "lat": 51.480240330686634, "lng": -1.0052382946014407 }
                },
                {
                    "name": "Right FW",
                    "type": "bunker",
                    "coord": { "lat": 51.480009809632904, "lng": -1.0048252344131472 },
                    "key": "2",
                    "back": { "lat": 51.480120058977889, "lng": -1.0048145055770876 },
                    "front": { "lat": 51.4799463326164, "lng": -1.0048198699951174 }
                },
                {
                    "name": "Layup",
                    "type": "checkpoint",
                    "coord": { "lat": 51.480062301411799, "lng": -1.0051497817039492 },
                    "key": "1",
                    "back": { "lat": 51.479917037102631, "lng": -1.0051900148391726 },
                    "front": { "lat": 51.480207565720967, "lng": -1.0051095485687258 }
                }
            ],
            "green": { "front": { "lat": 51.482066461220917, "lng": -1.0040473937988283 }, "back": { "lat": 51.482285182400545, "lng": -1.0037738084793093 } },
            "pins": [{ "key": "", "quadrant": "", "coord": { "lat": 51.482175821810728, "lng": -1.0039106011390688 } }]
        },
        {
            "no": 8,
            "tees": [
                { "colour": "Black", "coords": { "lat": 51.483378954977248, "lng": -1.002982556819916 }, "par": 3, "parL": null },
                { "colour": "Gold", "coords": { "lat": 51.483606194408949, "lng": -1.0032239556312563 }, "par": 3, "parL": null },
                { "colour": "Blue", "coords": { "lat": 51.483853483092133, "lng": -1.0032722353935244 }, "par": 3, "parL": null },
                { "colour": "Green", "coords": { "lat": 51.483880216923502, "lng": -1.0035189986228945 }, "par": 3, "parL": null },
                { "colour": "Orange", "coords": { "lat": 51.484177629740444, "lng": -1.0036852955818178 }, "par": 3, "parL": null }
            ],
            "par": 3,
            "parL": null,
            "si": 8,
            "siL": 8,
            "checkpoints": [
                {
                    "type": "bunker",
                    "name": "Left Green",
                    "key": "bunker-Left Green",
                    "back": { "lat": 51.484878266151412, "lng": -1.0049003362655642 },
                    "coord": { "lat": 51.484945463328032, "lng": -1.0049365460872652 },
                    "front": { "lat": 51.485012660504644, "lng": -1.0049727559089663 }
                },
                {
                    "type": "bunker",
                    "name": "Back Green",
                    "key": "bunker-Back Green",
                    "back": { "lat": 51.485031024919671, "lng": -1.0047139227390292 },
                    "coord": { "lat": 51.485065666851085, "lng": -1.0047212988138201 },
                    "front": { "lat": 51.485100308782492, "lng": -1.0047286748886111 }
                },
                {
                    "name": "Water",
                    "type": "water",
                    "coord": { "lat": 51.484640652612015, "lng": -1.0040400177240374 },
                    "key": "1",
                    "back": { "lat": 51.484429877450339, "lng": -1.0036651790142062 },
                    "front": { "lat": 51.484851427773691, "lng": -1.0044148564338686 }
                }
            ],
            "green": { "front": { "lat": 51.484813990451144, "lng": -1.0046495497226717 }, "back": { "lat": 51.485009321519307, "lng": -1.0046844184398653 } },
            "pins": [{ "key": "", "quadrant": "", "coord": { "lat": 51.484911655985229, "lng": -1.0046669840812685 } }]
        },
        {
            "no": 9,
            "tees": [
                { "colour": "Black", "coords": { "lat": 51.485700474098188, "lng": -1.0059008002281191 }, "par": 4, "parL": null },
                { "colour": "Gold", "coords": { "lat": 51.485770647529733, "lng": -1.0057774186134341 }, "par": 4, "parL": null },
                { "colour": "Blue", "coords": { "lat": 51.486011241332328, "lng": -1.0057398676872256 }, "par": 4, "parL": null },
                { "colour": "Green", "coords": { "lat": 51.485984508750256, "lng": -1.0055145621299746 }, "par": 4, "parL": null },
                { "colour": "Orange", "coords": { "lat": 51.48600455818827, "lng": -1.005305349826813 }, "par": 4, "parL": null }
            ],
            "par": 4,
            "parL": null,
            "si": 14,
            "siL": 14,
            "checkpoints": [
                {
                    "type": "bunker",
                    "name": "Left Green",
                    "key": "bunker-Left Green",
                    "back": { "lat": 51.487993573557041, "lng": -1.003457307815552 },
                    "coord": { "lat": 51.488039898901313, "lng": -1.0034164041280749 },
                    "front": { "lat": 51.488086224245585, "lng": -1.0033755004405978 }
                },
                {
                    "type": "bunker",
                    "name": "Right Green",
                    "key": "bunker-Right Green",
                    "back": { "lat": 51.487897583906388, "lng": -1.003081798553467 },
                    "coord": { "lat": 51.48797395823307, "lng": -1.0029939562082293 },
                    "front": { "lat": 51.488050332559745, "lng": -1.0029061138629916 }
                },
                {
                    "type": "bunker",
                    "name": "Right FW",
                    "key": "bunker-Right FW",
                    "back": { "lat": 51.487226485399134, "lng": -1.0030415654182436 },
                    "coord": { "lat": 51.487261543014881, "lng": -1.0030167549848559 },
                    "front": { "lat": 51.487296600630629, "lng": -1.0029919445514681 }
                },
                {
                    "type": "bunker",
                    "name": "Left FW",
                    "key": "bunker-Left FW",
                    "back": { "lat": 51.487139675915515, "lng": -1.0037858784198763 },
                    "coord": { "lat": 51.487249857021823, "lng": -1.0037235170602801 },
                    "front": { "lat": 51.487360038128131, "lng": -1.0036611557006838 }
                },
                {
                    "name": "Layup",
                    "type": "checkpoint",
                    "coord": { "lat": 51.487087089285687, "lng": -1.0033272206783297 },
                    "key": "0",
                    "front": { "lat": 51.487143849452167, "lng": -1.0030978918075564 },
                    "back": { "lat": 51.487030329119207, "lng": -1.003556549549103 }
                }
            ],
            "green": { "front": { "lat": 51.487893870569003, "lng": -1.0033352673053744 }, "back": { "lat": 51.488139269815562, "lng": -1.003018766641617 } },
            "pins": [{ "key": "", "quadrant": "", "coord": { "lat": 51.488016570192286, "lng": -1.0031770169734957 } }]
        },
        {
            "no": 10,
            "tees": [
                { "colour": "Black", "coords": { "lat": 51.48921169730513, "lng": -1.0017809271812441 }, "par": 4, "parL": null },
                { "colour": "Gold", "coords": { "lat": 51.488810735074381, "lng": -1.0019525885581972 }, "par": 4, "parL": null },
                { "colour": "Blue", "coords": { "lat": 51.488703811217306, "lng": -1.0020008683204653 }, "par": 4, "parL": null },
                { "colour": "Green", "coords": { "lat": 51.488556790504418, "lng": -1.0020062327384951 }, "par": 4, "parL": null },
                { "colour": "Orange", "coords": { "lat": 51.488316210133405, "lng": -1.0019204020500185 }, "par": 4, "parL": null }
            ],
            "par": 4,
            "parL": null,
            "si": 5,
            "siL": 5,
            "checkpoints": [
                {
                    "type": "bunker",
                    "name": "Middle FW",
                    "key": "bunker-Middle FW",
                    "back": { "lat": 51.486554395851776, "lng": -1.0009172558784487 },
                    "coord": { "lat": 51.486470923890749, "lng": -1.0009306669235232 },
                    "front": { "lat": 51.486387451929716, "lng": -1.0009440779685976 }
                },
                {
                    "type": "bunker",
                    "name": "Right FW",
                    "key": "bunker-Right FW",
                    "back": { "lat": 51.486510990490828, "lng": -1.001359820365906 },
                    "coord": { "lat": 51.486443378161553, "lng": -1.0013450682163241 },
                    "front": { "lat": 51.486375765832271, "lng": -1.0013303160667422 }
                },
                {
                    "type": "checkpoint",
                    "name": "Layup",
                    "key": "checkpoint-Layup",
                    "back": { "lat": 51.486716596783502, "lng": -1.0012364387512209 },
                    "coord": { "lat": 51.486608083560569, "lng": -1.0011063516139986 },
                    "front": { "lat": 51.486499570337628, "lng": -1.0009762644767763 }
                },
                {
                    "type": "bunker",
                    "name": "Left FW",
                    "key": "bunker-Left FW",
                    "back": { "lat": 51.486916958029909, "lng": -1.0011157393455508 },
                    "coord": { "lat": 51.486861032294499, "lng": -1.0010071098804476 },
                    "front": { "lat": 51.486805106559082, "lng": -1.0008984804153445 }
                }
            ],
            "green": { "front": { "lat": 51.48591091020851, "lng": -1.0004666447639468 }, "back": { "lat": 51.48572043980041, "lng": -1.0004130005836489 } },
            "pins": [{ "key": "", "quadrant": "", "coord": { "lat": 51.485805883485504, "lng": -1.0004532337188723 } }]
        },
        {
            "no": 11,
            "tees": [
                { "colour": "Black", "coords": { "lat": 51.485931524338227, "lng": -0.99986046552658092 }, "par": 5, "parL": null },
                { "colour": "Gold", "coords": { "lat": 51.485817910557671, "lng": -0.99985510110855114 }, "par": 5, "parL": null },
                { "colour": "Blue", "coords": { "lat": 51.485667538942266, "lng": -0.99984437227249157 }, "par": 5, "parL": null },
                { "colour": "Green", "coords": { "lat": 51.485360110985305, "lng": -0.99980682134628307 }, "par": 5, "parL": null },
                { "colour": "Orange", "coords": { "lat": 51.485056022597554, "lng": -0.99972099065780651 }, "par": 5, "parL": null }
            ],
            "par": 5,
            "parL": null,
            "si": 9,
            "siL": 9,
            "checkpoints": [
                {
                    "type": "bunker",
                    "name": "Right Green",
                    "key": "bunker-Right Green",
                    "back": { "lat": 51.482086156833411, "lng": -1.0004197061061861 },
                    "coord": { "lat": 51.481998502677854, "lng": -1.0005202889442446 },
                    "front": { "lat": 51.481910848522297, "lng": -1.0006208717823031 }
                },
                {
                    "type": "bunker",
                    "name": "Left Green",
                    "key": "bunker-Left Green",
                    "back": { "lat": 51.481899996080855, "lng": -1.0000884532928469 },
                    "coord": { "lat": 51.481845733802786, "lng": -1.0001273453235628 },
                    "front": { "lat": 51.481791471524723, "lng": -1.0001662373542788 }
                },
                {
                    "name": "Middle FW",
                    "type": "bunker",
                    "coord": { "lat": 51.4825276786394, "lng": -0.99954597651958477 },
                    "key": "3",
                    "back": { "lat": 51.482572340000424, "lng": -0.99949166178703319 },
                    "front": { "lat": 51.482483017278376, "lng": -0.99960029125213634 }
                },
                {
                    "name": "Layup",
                    "type": "checkpoint",
                    "coord": { "lat": 51.482395179265303, "lng": -0.99924623966217052 },
                    "key": "0",
                    "front": { "lat": 51.482600603752537, "lng": -0.99937230348587047 },
                    "back": { "lat": 51.482236497490113, "lng": -0.99916309118270885 }
                },
                {
                    "name": "Left FW",
                    "type": "bunker",
                    "coord": { "lat": 51.483640723476441, "lng": -0.9993790090084077 },
                    "key": "2",
                    "back": { "lat": 51.48369999224726, "lng": -0.99938303232193004 },
                    "front": { "lat": 51.483581454705622, "lng": -0.99937498569488536 }
                },
                {
                    "name": "Right FW",
                    "type": "bunker",
                    "coord": { "lat": 51.48386870691256, "lng": -0.99996238946914684 },
                    "key": "1",
                    "back": { "lat": 51.484049016637819, "lng": -0.99998652935028087 },
                    "front": { "lat": 51.483688397187294, "lng": -0.99993824958801281 }
                }
            ],
            "green": { "front": { "lat": 51.482021088261291, "lng": -1.0002815723419192 }, "back": { "lat": 51.481754785943046, "lng": -1.0004304349422457 } },
            "pins": [{ "key": "", "quadrant": "", "coord": { "lat": 51.481887937102172, "lng": -1.0003560036420824 } }]
        },
        {
            "no": 12,
            "tees": [
                { "colour": "Black", "coords": { "lat": 51.481167666240346, "lng": -1.0016575455665591 }, "par": 4, "parL": null },
                { "colour": "Gold", "coords": { "lat": 51.481045472553902, "lng": -1.0015797615051272 }, "par": 4, "parL": null },
                { "colour": "Blue", "coords": { "lat": 51.48095044048641, "lng": -1.0017487406730654 }, "par": 4, "parL": null },
                { "colour": "Green", "coords": { "lat": 51.480699794100026, "lng": -1.0015663504600527 }, "par": 4, "parL": null },
                { "colour": "Orange", "coords": { "lat": 51.480475882163226, "lng": -1.0017916560173037 }, "par": 4, "parL": null }
            ],
            "par": 4,
            "parL": null,
            "si": 3,
            "siL": 3,
            "checkpoints": [
                {
                    "type": "bunker",
                    "name": "Left Green",
                    "key": "bunker-Left Green",
                    "back": { "lat": 51.477880107338244, "lng": -1.0010701417922976 },
                    "coord": { "lat": 51.477848381995194, "lng": -1.0010144859552386 },
                    "front": { "lat": 51.477816656652145, "lng": -1.0009588301181795 }
                },
                {
                    "type": "bunker",
                    "name": "Right Green",
                    "key": "bunker-Right Green",
                    "back": { "lat": 51.47776572906394, "lng": -1.001422852277756 },
                    "coord": { "lat": 51.477720645555486, "lng": -1.0014208406209948 },
                    "front": { "lat": 51.477675562047033, "lng": -1.0014188289642336 }
                },
                {
                    "type": "bunker",
                    "name": "Right FW",
                    "key": "bunker-Right FW",
                    "back": { "lat": 51.478780869311869, "lng": -1.0015153884887698 },
                    "coord": { "lat": 51.478746640010598, "lng": -1.0015314817428591 },
                    "front": { "lat": 51.478712410709328, "lng": -1.0015475749969485 }
                },
                {
                    "type": "bunker",
                    "name": "Left FW",
                    "key": "bunker-Left FW",
                    "back": { "lat": 51.479017969043447, "lng": -1.0012739896774294 },
                    "coord": { "lat": 51.478944501593602, "lng": -1.0011760890483858 },
                    "front": { "lat": 51.478871034143758, "lng": -1.0010781884193423 }
                }
            ],
            "green": { "front": { "lat": 51.477876371417395, "lng": -1.0012552142143252 }, "back": { "lat": 51.477655787803108, "lng": -1.0010567307472231 } },
            "pins": [{ "key": "", "quadrant": "", "coord": { "lat": 51.477798433688577, "lng": -1.0011506080627444 } }]
        },
        {
            "no": 13,
            "tees": [
                { "colour": "Black", "coords": { "lat": 51.479308444780997, "lng": -0.99887073040008556 }, "par": 4, "parL": null },
                { "colour": "Gold", "coords": { "lat": 51.478630062462337, "lng": -1.0001689195632937 }, "par": 4, "parL": null },
                { "colour": "Blue", "coords": { "lat": 51.478436291088386, "lng": -1.0000026226043703 }, "par": 4, "parL": null },
                { "colour": "Green", "coords": { "lat": 51.478242445081683, "lng": -0.99994361400604259 }, "par": 4, "parL": null },
                { "colour": "Orange", "coords": { "lat": 51.477993445556841, "lng": -0.99996238946914684 }, "par": 4, "parL": null }
            ],
            "par": 4,
            "parL": null,
            "si": 15,
            "siL": 15,
            "checkpoints": [
                {
                    "type": "bunker",
                    "name": "Left Green",
                    "key": "bunker-Left Green",
                    "back": { "lat": 51.475910439938311, "lng": -1.0004773736000063 },
                    "coord": { "lat": 51.475770591595406, "lng": -1.0004565864801409 },
                    "front": { "lat": 51.475630743252502, "lng": -1.0004357993602755 }
                },
                {
                    "type": "bunker",
                    "name": "Right Green",
                    "key": "bunker-Right Green",
                    "back": { "lat": 51.475853897106688, "lng": -1.0008206963539126 },
                    "coord": { "lat": 51.475820083066424, "lng": -1.000817343592644 },
                    "front": { "lat": 51.475786269026159, "lng": -1.0008139908313753 }
                },
                {
                    "type": "bunker",
                    "name": "Middle FW",
                    "key": "bunker-Middle FW",
                    "back": { "lat": 51.476116059335247, "lng": -1.0003446042537691 },
                    "coord": { "lat": 51.476082245489337, "lng": -1.0003720968961718 },
                    "front": { "lat": 51.476048431643434, "lng": -1.0003995895385744 }
                },
                {
                    "type": "bunker",
                    "name": "Middle FW",
                    "key": "bunker-Middle FW",
                    "back": { "lat": 51.476462545319343, "lng": -1.0003124177455904 },
                    "coord": { "lat": 51.476376550167302, "lng": -1.0003204643726351 },
                    "front": { "lat": 51.476290555015254, "lng": -1.0003285109996798 }
                }
            ],
            "green": { "front": { "lat": 51.4758248101368, "lng": -1.0006007552146914 }, "back": { "lat": 51.475607558935245, "lng": -1.0007134079933169 } },
            "pins": [{ "key": "", "quadrant": "", "coord": { "lat": 51.475688083050827, "lng": -1.0006785392761233 } }]
        },
        {
            "no": 14,
            "tees": [
                { "colour": "Black", "coords": { "lat": 51.475435894043585, "lng": -1.0021162033081057 }, "par": 5, "parL": null },
                { "colour": "Gold", "coords": { "lat": 51.475493693517578, "lng": -1.0023120045661928 }, "par": 5, "parL": null },
                { "colour": "Blue", "coords": { "lat": 51.475602961864055, "lng": -1.0020679235458376 }, "par": 5, "parL": null },
                { "colour": "Green", "coords": { "lat": 51.476061888200427, "lng": -1.0021510720252993 }, "par": 5, "parL": null },
                { "colour": "Orange", "coords": { "lat": 51.476180991939245, "lng": -1.002309322357178 }, "par": 5, "parL": null }
            ],
            "par": 5,
            "parL": null,
            "si": 13,
            "siL": 13,
            "checkpoints": [
                {
                    "type": "bunker",
                    "name": "Right Green",
                    "key": "bunker-Right Green",
                    "back": { "lat": 51.47920367016458, "lng": -1.0034868121147158 },
                    "coord": { "lat": 51.479250421864535, "lng": -1.0035330802202227 },
                    "front": { "lat": 51.479297173564497, "lng": -1.0035793483257296 }
                },
                {
                    "type": "bunker",
                    "name": "Left Green",
                    "key": "bunker-Left Green",
                    "back": { "lat": 51.479274632583838, "lng": -1.0040044784545901 },
                    "coord": { "lat": 51.479405703867812, "lng": -1.004023924469948 },
                    "front": { "lat": 51.479536775151786, "lng": -1.004043370485306 }
                },
                {
                    "type": "bunker",
                    "name": "Left FW",
                    "key": "bunker-Left FW",
                    "back": { "lat": 51.478746848920103, "lng": -1.0037389397621157 },
                    "coord": { "lat": 51.478852876020937, "lng": -1.0038247704505923 },
                    "front": { "lat": 51.478958903121764, "lng": -1.0039106011390688 }
                },
                {
                    "name": "Bunker",
                    "type": "bunker",
                    "coord": { "lat": 51.477570892330021, "lng": -1.0030442476272585 },
                    "key": "1",
                    "back": { "lat": 51.477671124377913, "lng": -1.0030764341354372 },
                    "front": { "lat": 51.477500729765438, "lng": -1.0030710697174074 }
                }
            ],
            "green": { "front": { "lat": 51.479243532445402, "lng": -1.0037550330162051 }, "back": { "lat": 51.479490844785623, "lng": -1.0038086771965029 } },
            "pins": [{ "key": "", "quadrant": "", "coord": { "lat": 51.479359848168095, "lng": -1.0037577152252199 } }]
        },
        {
            "no": 15,
            "tees": [
                { "colour": "Black", "coords": { "lat": 51.480084588441677, "lng": -1.0036906599998476 }, "par": 3, "parL": null },
                { "colour": "Gold", "coords": { "lat": 51.480298476329423, "lng": -1.0036423802375796 }, "par": 3, "parL": null },
                { "colour": "Blue", "coords": { "lat": 51.480435497730419, "lng": -1.0035404562950136 }, "par": 3, "parL": null },
                { "colour": "Green", "coords": { "lat": 51.480625990213596, "lng": -1.0034975409507754 }, "par": 3, "parL": null },
                { "colour": "Orange", "coords": { "lat": 51.480941911569502, "lng": -1.0033178329467776 }, "par": 3, "parL": null }
            ],
            "par": 3,
            "parL": null,
            "si": 11,
            "siL": 11,
            "checkpoints": [
                {
                    "type": "bunker",
                    "name": "Left Green",
                    "key": "bunker-Left Green",
                    "back": { "lat": 51.482062960493991, "lng": -1.0035645961761477 },
                    "coord": { "lat": 51.482116387650706, "lng": -1.0035498440265658 },
                    "front": { "lat": 51.482169814807428, "lng": -1.0035350918769839 }
                },
                {
                    "type": "bunker",
                    "name": "Right Green",
                    "key": "bunker-Right Green",
                    "back": { "lat": 51.481919374616069, "lng": -1.0031434893608095 },
                    "coord": { "lat": 51.482027898738721, "lng": -1.0031341016292574 },
                    "front": { "lat": 51.482136422861366, "lng": -1.0031247138977053 }
                }
            ],
            "green": { "front": { "lat": 51.481978610127065, "lng": -1.0033996403217318 }, "back": { "lat": 51.482259937481324, "lng": -1.0033138096332552 } },
            "pins": [{ "key": "", "quadrant": "", "coord": { "lat": 51.482119273804194, "lng": -1.0033567249774935 } }]
        },
        {
            "no": 16,
            "tees": [
                { "colour": "Black", "coords": { "lat": 51.481864940480932, "lng": -1.0014483332633974 }, "par": 4, "parL": null },
                { "colour": "Gold", "coords": { "lat": 51.482058768855097, "lng": -1.0015019774436953 }, "par": 4, "parL": null },
                { "colour": "Blue", "coords": { "lat": 51.482175733854731, "lng": -1.0014912486076357 }, "par": 4, "parL": null },
                { "colour": "Green", "coords": { "lat": 51.48286080854264, "lng": -1.0024192929267886 }, "par": 4, "parL": null },
                { "colour": "Orange", "coords": { "lat": 51.483034581949056, "lng": -1.0024139285087588 }, "par": 4, "parL": null }
            ],
            "par": 4,
            "parL": null,
            "si": 1,
            "siL": 1,
            "checkpoints": [
                {
                    "type": "bunker",
                    "name": "Right Green",
                    "key": "bunker-Right Green",
                    "back": { "lat": 51.485647537696067, "lng": -1.0018050670623782 },
                    "coord": { "lat": 51.48575020983094, "lng": -1.0017313063144686 },
                    "front": { "lat": 51.485852881965819, "lng": -1.0016575455665591 }
                },
                {
                    "type": "bunker",
                    "name": "Left Green",
                    "key": "bunker-Left Green",
                    "back": { "lat": 51.485869576581237, "lng": -1.0021376609802248 },
                    "coord": { "lat": 51.485917156176868, "lng": -1.0020746290683749 },
                    "front": { "lat": 51.485964735772498, "lng": -1.0020115971565249 }
                },
                {
                    "type": "bunker",
                    "name": "Middle FW",
                    "key": "bunker-Middle FW",
                    "back": { "lat": 51.485092089655268, "lng": -1.0020598769187929 },
                    "coord": { "lat": 51.485162208114986, "lng": -1.0019767284393313 },
                    "front": { "lat": 51.485232326574703, "lng": -1.0018935799598696 }
                },
                {
                    "type": "bunker",
                    "name": "Middle FW",
                    "key": "bunker-Middle FW",
                    "back": { "lat": 51.484140470595008, "lng": -1.0017916560173037 },
                    "coord": { "lat": 51.484247319915433, "lng": -1.001858711242676 },
                    "front": { "lat": 51.484354169235857, "lng": -1.0019257664680483 }
                }
            ],
            "green": { "front": { "lat": 51.485694405367546, "lng": -1.0019874572753908 }, "back": { "lat": 51.485998247467691, "lng": -1.0018533468246462 } },
            "pins": [{ "key": "", "quadrant": "", "coord": { "lat": 51.485846326417615, "lng": -1.0019204020500185 } }]
        },
        {
            "no": 17,
            "tees": [
                { "colour": "Black", "coords": { "lat": 51.486449114836176, "lng": -1.0033527016639712 }, "par": 3, "parL": null },
                { "colour": "Gold", "coords": { "lat": 51.486225231127513, "lng": -1.0033366084098818 }, "par": 3, "parL": null },
                { "colour": "Blue", "coords": { "lat": 51.486104934949459, "lng": -1.0032454133033755 }, "par": 3, "parL": null },
                { "colour": "Green", "coords": { "lat": 51.485947881128254, "lng": -1.0034653544425967 }, "par": 3, "parL": null },
                { "colour": "Orange", "coords": { "lat": 51.485790826766106, "lng": -1.0035243630409243 }, "par": 3, "parL": null }
            ],
            "par": 3,
            "parL": null,
            "si": 17,
            "siL": 17,
            "checkpoints": [
                {
                    "type": "bunker",
                    "name": "Right Green",
                    "key": "bunker-Right Green",
                    "back": { "lat": 51.485572965300612, "lng": -1.004518121480942 },
                    "coord": { "lat": 51.485543749520176, "lng": -1.0046079754829409 },
                    "front": { "lat": 51.485514533739746, "lng": -1.0046978294849398 }
                },
                {
                    "type": "bunker",
                    "name": "Left Green",
                    "key": "bunker-Right Green",
                    "back": { "lat": 51.485432109352161, "lng": -1.0042485594749453 },
                    "coord": { "lat": 51.485351139561544, "lng": -1.0042753815650942 },
                    "front": { "lat": 51.485270169770935, "lng": -1.0043022036552431 }
                }
            ],
            "green": { "front": { "lat": 51.485418538870107, "lng": -1.0045221447944643 }, "back": { "lat": 51.485315865872806, "lng": -1.0046790540218355 } },
            "pins": [{ "key": "", "quadrant": "", "coord": { "lat": 51.485367202371457, "lng": -1.0046005994081499 } }]
        },
        {
            "no": 18,
            "tees": [
                { "colour": "Black", "coords": { "lat": 51.485242751617605, "lng": -1.0067752003669741 }, "par": 4, "parL": null },
                { "colour": "Gold", "coords": { "lat": 51.485493373035801, "lng": -1.0064372420310976 }, "par": 4, "parL": null },
                { "colour": "Blue", "coords": { "lat": 51.485620354028626, "lng": -1.0065338015556338 }, "par": 4, "parL": null },
                { "colour": "Green", "coords": { "lat": 51.485663794813391, "lng": -1.0070112347602846 }, "par": 4, "parL": null },
                { "colour": "Orange", "coords": { "lat": 51.485874314953385, "lng": -1.0070648789405825 }, "par": 4, "parL": null }
            ],
            "par": 4,
            "parL": null,
            "si": 7,
            "siL": 7,
            "checkpoints": [
                {
                    "type": "bunker",
                    "name": "Left FW",
                    "key": "bunker-Left FW",
                    "back": { "lat": 51.488402522124815, "lng": -1.0070970654487612 },
                    "coord": { "lat": 51.488440082885091, "lng": -1.0070065408945086 },
                    "front": { "lat": 51.488477643645375, "lng": -1.006916016340256 }
                },
                {
                    "type": "bunker",
                    "name": "Left Green",
                    "key": "bunker-Left Green",
                    "back": { "lat": 51.488544271603232, "lng": -1.0069247335195544 },
                    "coord": { "lat": 51.488645685198662, "lng": -1.0069039463996889 },
                    "front": { "lat": 51.488747098794093, "lng": -1.0068831592798235 }
                },
                {
                    "type": "bunker",
                    "name": "Right FW",
                    "key": "bunker-Right FW",
                    "back": { "lat": 51.487195201255993, "lng": -1.0069119930267336 },
                    "coord": { "lat": 51.487255300034079, "lng": -1.0068395733833315 },
                    "front": { "lat": 51.487315398812164, "lng": -1.0067671537399294 }
                }
            ],
            "green": { "front": { "lat": 51.488451205274536, "lng": -1.006738990545273 }, "back": { "lat": 51.488741256818834, "lng": -1.0066746175289156 } },
            "pins": [{ "key": "", "quadrant": "", "coord": { "lat": 51.488596231046685, "lng": -1.0067068040370943 } }]
        }
    ]
}
